[
  {
    "ApplyEyeMakeup": [
      "Lipstick"
    ]
  },
  {
    "ApplyLipstick": [
      "Lipstick"
    ]
  },
  {
    "Archery": [
      "Curling"
    ]
  },
  {
    "BabyCrawling": [
      "Stroller"
    ]
  },
  {
    "BalanceBeam": [
      "Dumbbell"
    ]
  },
  {
    "BandMarching": [
      "Drum"
    ]
  },
  {
    "BaseballPitch": [
      "Baseball"
    ]
  },
  {
    "Basketball": [
      "Basketball"
    ]
  },
  {
    "BasketballDunk": [
      "Basketball"
    ]
  },
  {
    "BenchPress": [
      "Bench"
    ]
  },
  {
    "Biking": [
      "Bicycle"
    ]
  },
  {
    "Billiards": [
      "Billiards"
    ]
  },
  {
    "BlowDryHair": [
      "Hair Dryer"
    ]
  },
  {
    "BlowingCandles": [
      "Candle"
    ]
  },
  {
    "BodyWeightSquats": [
      "Dumbbell"
    ]
  },
  {
    "Bowling": [
      "Curling"
    ]
  },
  {
    "BoxingPunchingBag": [
      "Baseball Bat"
    ]
  },
  {
    "BoxingSpeedBag": [
      "Baseball Glove"
    ]
  },
  {
    "BreastStroke": [
      "Table Tennis"
    ]
  },
  {
    "BrushingTeeth": [
      "Toothbrush"
    ]
  },
  {
    "CleanAndJerk": [
      "Brush"
    ]
  },
  {
    "CliffDiving": [
      "Skiboard"
    ]
  },
  {
    "CricketBowling": [
      "Tennis"
    ]
  },
  {
    "CricketShot": [
      "Golf Ball"
    ]
  },
  {
    "CuttingInKitchen": [
      "Cutting/chopping Board"
    ]
  },
  {
    "Diving": [
      "Seal"
    ]
  },
  {
    "Drumming": [
      "Drum"
    ]
  },
  {
    "Fencing": [
      "Volleyball"
    ]
  },
  {
    "FieldHockeyPenalty": [
      "Soccer"
    ]
  },
  {
    "FloorGymnastics": [
      "Curling"
    ]
  },
  {
    "FrisbeeCatch": [
      "Frisbee"
    ]
  },
  {
    "FrontCrawl": [
      "Ladder"
    ]
  },
  {
    "GolfSwing": [
      "Swing"
    ]
  },
  {
    "Haircut": [
      "Comb"
    ]
  },
  {
    "HammerThrow": [
      "Hammer"
    ]
  },
  {
    "Hammering": [
      "Hammer"
    ]
  },
  {
    "HandstandPushups": [
      "Dumbbell"
    ]
  },
  {
    "HandstandWalking": [
      "High Heels"
    ]
  },
  {
    "HeadMassage": [
      "Pillow"
    ]
  },
  {
    "HighJump": [
      "High Heels"
    ]
  },
  {
    "HorseRace": [
      "Horse"
    ]
  },
  {
    "HorseRiding": [
      "Horse"
    ]
  },
  {
    "HulaHoop": [
      "Kite"
    ]
  },
  {
    "IceDancing": [
      "Curling"
    ]
  },
  {
    "JavelinThrow": [
      "Volleyball"
    ]
  },
  {
    "JugglingBalls": [
      "Other Balls"
    ]
  },
  {
    "JumpRope": [
      "Frisbee"
    ]
  },
  {
    "JumpingJack": [
      "Skateboard"
    ]
  },
  {
    "Kayaking": [
      "Paddle"
    ]
  },
  {
    "Knitting": [
      "Curling"
    ]
  },
  {
    "LongJump": [
      "Hurdle"
    ]
  },
  {
    "Lunges": [
      "Dumbbell"
    ]
  },
  {
    "MilitaryParade": [
      "Street Lights"
    ]
  },
  {
    "Mixing": [
      "Drum"
    ]
  },
  {
    "MoppingFloor": [
      "Mop"
    ]
  },
  {
    "Nunchucks": [
      "Slippers"
    ]
  },
  {
    "ParallelBars": [
      "Barbell"
    ]
  },
  {
    "PizzaTossing": [
      "Pizza"
    ]
  },
  {
    "PlayingCello": [
      "Cello"
    ]
  },
  {
    "PlayingDaf": [
      "Table Tennis"
    ]
  },
  {
    "PlayingDhol": [
      "Volleyball"
    ]
  },
  {
    "PlayingFlute": [
      "Flute"
    ]
  },
  {
    "PlayingGuitar": [
      "Guitar"
    ]
  },
  {
    "PlayingPiano": [
      "Piano"
    ]
  },
  {
    "PlayingSitar": [
      "Violin"
    ]
  },
  {
    "PlayingTabla": [
      "Table Tennis"
    ]
  },
  {
    "PlayingViolin": [
      "Violin"
    ]
  },
  {
    "PoleVault": [
      "Skiboard"
    ]
  },
  {
    "PommelHorse": [
      "Horse"
    ]
  },
  {
    "PullUps": [
      "Dumbbell"
    ]
  },
  {
    "Punch": [
      "Hammer"
    ]
  },
  {
    "PushUps": [
      "Dumbbell"
    ]
  },
  {
    "Rafting": [
      "Skiboard"
    ]
  },
  {
    "RockClimbingIndoor": [
      "Ladder"
    ]
  },
  {
    "RopeClimbing": [
      "Ladder"
    ]
  },
  {
    "Rowing": [
      "Curling"
    ]
  },
  {
    "SalsaSpin": [
      "Skateboard"
    ]
  },
  {
    "ShavingBeard": [
      "Comb"
    ]
  },
  {
    "Shotput": [
      "Gun"
    ]
  },
  {
    "SkateBoarding": [
      "Skateboard"
    ]
  },
  {
    "Skiing": [
      "Skiboard"
    ]
  },
  {
    "Skijet": [
      "Skiboard"
    ]
  },
  {
    "SkyDiving": [
      "Skiboard"
    ]
  },
  {
    "SoccerJuggling": [
      "Soccer"
    ]
  },
  {
    "SoccerPenalty": [
      "Soccer"
    ]
  },
  {
    "StillRings": [
      "Ring"
    ]
  },
  {
    "SumoWrestling": [
      "Curling"
    ]
  },
  {
    "Surfing": [
      "Surfboard"
    ]
  },
  {
    "Swing": [
      "Swing"
    ]
  },
  {
    "TableTennisShot": [
      "Table Tennis"
    ]
  },
  {
    "TaiChi": [
      "Table Tennis"
    ]
  },
  {
    "TennisSwing": [
      "Swing"
    ]
  },
  {
    "ThrowDiscus": [
      "Volleyball"
    ]
  },
  {
    "TrampolineJumping": [
      "Skiboard"
    ]
  },
  {
    "Typing": [
      "Keyboard"
    ]
  },
  {
    "UnevenBars": [
      "Barbell"
    ]
  },
  {
    "VolleyballSpiking": [
      "Volleyball"
    ]
  },
  {
    "WalkingWithDog": [
      "Dog"
    ]
  },
  {
    "WallPushups": [
      "Dumbbell"
    ]
  },
  {
    "WritingOnBoard": [
      "Blackboard/Whiteboard"
    ]
  },
  {
    "YoYo": [
      "Yak"
    ]
  }
]